[
  {
    "github": "Vendicated",
    "name": "V"
  },
  {
    "github": "wildras",
    "name": "WildRas"
  },
  {
    "github": "colorpeak",
    "name": "Takeshi Kimura"
  },
  {
    "github": "Erisa",
    "name": "Erisa A"
  },
  {
    "github": "auddis",
    "name": null
  },
  {
    "github": "haniakil",
    "name": null
  },
  {
    "github": "p3u1",
    "name": "Paul Kennedy"
  },
  {
    "github": "sent1n3l",
    "name": null
  },
  {
    "github": "BoardTM",
    "name": "Board"
  },
  {
    "github": "marcinmajsc",
    "name": null
  },
  {
    "github": "jtutrow23",
    "name": null
  },
  {
    "github": "rp1231",
    "name": null
  },
  {
    "github": "FirleFrantz",
    "name": "Firlefrantz"
  },
  {
    "github": "BrandonPlays",
    "name": "BrandonPlays"
  },
  {
    "github": "dorian-bucaille",
    "name": "Dorian Bucaille"
  },
  {
    "github": "QwertYapur",
    "name": null
  },
  {
    "github": "Shimenko",
    "name": "fiks"
  },
  {
    "github": "breadcat0314",
    "name": null
  },
  {
    "github": "CasperOng",
    "name": "Casper Ong NY"
  },
  {
    "github": "nikitawarren",
    "name": null
  },
  {
    "github": "chloecinders",
    "name": "Chloe"
  },
  {
    "github": "Win1876",
    "name": null
  },
  {
    "github": "Twfstunna",
    "name": "Twfstunna"
  },
  {
    "github": "mexy6",
    "name": "GareebSAG"
  },
  {
    "github": "actieven",
    "name": null
  },
  {
    "github": "TinyBeanDev",
    "name": "Tiny"
  },
  {
    "github": "Nikolas-Wos",
    "name": null
  },
  {
    "github": "ERSM222",
    "name": null
  },
  {
    "github": "RRookknneess",
    "name": null
  },
  {
    "github": "YouGottaBillieve",
    "name": null
  }
]
